modelpack-2.2.12.dist-info/WHEEL
modelpack-2.2.12.dist-info/entry_points.txt
modelpack-2.2.12.dist-info/METADATA
modelpack-2.2.12.dist-info/LICENSE.txt
modelpack-2.2.12.dist-info/RECORD
modelpack-2.2.12.dist-info/top_level.txt
deepview/modelpack/__init__.py
deepview/modelpack/datasets/darknet.cpython-39-x86_64-linux-gnu.so
deepview/modelpack/datasets/utils.cpython-39-x86_64-linux-gnu.so
deepview/modelpack/datasets/__init__.py
deepview/modelpack/datasets/attitude.cpython-39-x86_64-linux-gnu.so
deepview/modelpack/datasets/segmentation.cpython-39-x86_64-linux-gnu.so
deepview/modelpack/datasets/core.cpython-39-x86_64-linux-gnu.so
deepview/modelpack/datasets/tfrecord.cpython-39-x86_64-linux-gnu.so
deepview/modelpack/datasets/multitask.cpython-39-x86_64-linux-gnu.so
deepview/modelpack/trainer/__init__.py
deepview/modelpack/trainer/attitude.cpython-39-x86_64-linux-gnu.so
deepview/modelpack/trainer/__main__.py
deepview/modelpack/trainer/detection.cpython-39-x86_64-linux-gnu.so
deepview/modelpack/trainer/segmentation.cpython-39-x86_64-linux-gnu.so
deepview/modelpack/trainer/multitask.cpython-39-x86_64-linux-gnu.so
deepview/modelpack/losses/utils.cpython-39-x86_64-linux-gnu.so
deepview/modelpack/losses/__init__.py
deepview/modelpack/losses/attitude.cpython-39-x86_64-linux-gnu.so
deepview/modelpack/losses/segmentation.cpython-39-x86_64-linux-gnu.so
deepview/modelpack/losses/core.cpython-39-x86_64-linux-gnu.so
deepview/modelpack/license/__init__.py
deepview/modelpack/license/core.cpython-39-x86_64-linux-gnu.so
deepview/modelpack/models/__init__.py
deepview/modelpack/models/common.cpython-39-x86_64-linux-gnu.so
deepview/modelpack/models/core.cpython-39-x86_64-linux-gnu.so
deepview/modelpack/models/weights/coco-relu6-focus.h5
deepview/modelpack/models/weights/coco-leaky.h5
deepview/modelpack/models/weights/coco-relu6.h5
deepview/modelpack/schedulers/__init__.py
deepview/modelpack/schedulers/scheduler.cpython-39-x86_64-linux-gnu.so
deepview/modelpack/callbacks/__init__.py
deepview/modelpack/callbacks/tensorboard.cpython-39-x86_64-linux-gnu.so
deepview/modelpack/callbacks/core.cpython-39-x86_64-linux-gnu.so
deepview/modelpack/layers/__init__.py
