Metadata-Version: 2.1
Name: modelpack
Version: 2.2.12
Summary: DeepView ModelPack
Home-page: http://www.au-zone.com
Author: Au-Zone Technologies
Author-email: support@au-zone.com
License: PROPRIETARY
Platform: UNKNOWN
License-File: LICENSE.txt
Requires-Dist: tensorflow <2.16.0,>=2.8.0
Requires-Dist: albumentations ~=1.3.0
Requires-Dist: psutil >=5.8.0
Requires-Dist: pycryptodome >=3.14.0
Requires-Dist: tqdm >=4.64.0
Requires-Dist: PyYAML >=6.0
Requires-Dist: Pillow >=9
Requires-Dist: cryptography >=3.3.0
Requires-Dist: matplotlib >=3.5.0
Requires-Dist: scipy >=1.8.0
Requires-Dist: urllib3 >=1.26.0
Requires-Dist: deepview-validator ~=3.1.2
Requires-Dist: enum-actions >=0.1.0
